memvai/__init__.py
memvai/_base_client.py
memvai/_client.py
memvai/_compat.py
memvai/_constants.py
memvai/_exceptions.py
memvai/_files.py
memvai/_models.py
memvai/_qs.py
memvai/_resource.py
memvai/_response.py
memvai/_streaming.py
memvai/_types.py
memvai/_version.py
memvai/py.typed
memvai/_helpers/__init__.py
memvai/_helpers/batch_upload.py
memvai/_utils/__init__.py
memvai/_utils/_compat.py
memvai/_utils/_datetime_parse.py
memvai/_utils/_logs.py
memvai/_utils/_proxy.py
memvai/_utils/_reflection.py
memvai/_utils/_resources_proxy.py
memvai/_utils/_streams.py
memvai/_utils/_sync.py
memvai/_utils/_transform.py
memvai/_utils/_typing.py
memvai/_utils/_utils.py
memvai/lib/.keep
memvai/resources/__init__.py
memvai/resources/files.py
memvai/resources/graph.py
memvai/resources/memories.py
memvai/resources/spaces.py
memvai/resources/videos.py
memvai/resources/upload/__init__.py
memvai/resources/upload/batch.py
memvai/resources/upload/upload.py
memvai/types/__init__.py
memvai/types/file.py
memvai/types/file_delete_params.py
memvai/types/file_delete_response.py
memvai/types/file_download_params.py
memvai/types/file_download_response.py
memvai/types/file_list_params.py
memvai/types/file_list_response.py
memvai/types/file_retrieve_response.py
memvai/types/memory_add_params.py
memvai/types/memory_add_response.py
memvai/types/memory_search_params.py
memvai/types/memory_search_response.py
memvai/types/pagination.py
memvai/types/space.py
memvai/types/space_create_params.py
memvai/types/space_create_response.py
memvai/types/space_delete_params.py
memvai/types/space_delete_response.py
memvai/types/space_get_stats_response.py
memvai/types/space_list_response.py
memvai/types/space_retrieve_response.py
memvai/types/space_update_params.py
memvai/types/space_update_response.py
memvai/types/video_delete_params.py
memvai/types/video_delete_response.py
memvai/types/video_download_params.py
memvai/types/video_download_response.py
memvai/types/video_list_params.py
memvai-0.4.1.dist-info/METADATA
memvai-0.4.1.dist-info/WHEEL
memvai-0.4.1.dist-info/licenses/LICENSE
memvai-0.4.1.dist-info/RECORD
